{
  "configVersion": 1,
  "index": "/index.html",
  "assetGroups": [
    {
      "name": "app",
      "installMode": "prefetch",
      "updateMode": "prefetch",
      "urls": [
        "/0.bb6c5b448fdaaa623045.js",
        "/10.aabe3ebe97258744308d.js",
        "/5.39046f0f3da61be8b478.js",
        "/6.698d42e6a91885bb87f6.js",
        "/7.0f938d437943dbd115a3.js",
        "/8.bf6ded86d8b1a06b7f41.js",
        "/9.4e1145f1ba974a2b7d46.js",
        "/favicon.ico",
        "/index.html",
        "/main.c6dab967d020ecbf95fe.js",
        "/polyfills.eea33a3478150ded0b67.js",
        "/runtime.29054088d9cfdb04e3f5.js",
        "/scripts.286ee48665d1076626b8.js",
        "/styles.9da218e9c8e3bbce040a.css"
      ],
      "patterns": []
    },
    {
      "name": "assets",
      "installMode": "lazy",
      "updateMode": "prefetch",
      "urls": [
        "/assets/data/rin-sample-01.xml",
        "/assets/icon.png",
        "/assets/icons/icon-128x128.png",
        "/assets/icons/icon-144x144.png",
        "/assets/icons/icon-152x152.png",
        "/assets/icons/icon-192x192.png",
        "/assets/icons/icon-384x384.png",
        "/assets/icons/icon-512x512.png",
        "/assets/icons/icon-72x72.png",
        "/assets/icons/icon-96x96.png",
        "/assets/schemas/Audio.yaml",
        "/assets/schemas/Clip.yaml",
        "/assets/schemas/Person.yaml",
        "/assets/schemas/Photo.yaml",
        "/assets/schemas/Project.yaml",
        "/assets/schemas/file.yaml",
        "/assets/schemas/music-recording.yaml",
        "/assets/schemas/music-release.yaml",
        "/assets/schemas/music-work.yaml",
        "/assets/schemas/payment.yaml",
        "/assets/swagger/unsplash.json"
      ],
      "patterns": []
    }
  ],
  "dataGroups": [],
  "hashTable": {
    "/0.bb6c5b448fdaaa623045.js": "e9aecca04bb7d1c0710578f62cb49de22f3880cb",
    "/10.aabe3ebe97258744308d.js": "6045c4c52a9c18fda3fb8b9b977b2349c84c27c6",
    "/5.39046f0f3da61be8b478.js": "9865313101a36b1b5b8421bc62989e7d78f8e85d",
    "/6.698d42e6a91885bb87f6.js": "f9dd00be1c08590248151e44bb82fcb446fe55be",
    "/7.0f938d437943dbd115a3.js": "303bf1ccab7b424065da5930d3e4a0b847d22e21",
    "/8.bf6ded86d8b1a06b7f41.js": "d507fef3e99ddb2c5394be0751325190810d9035",
    "/9.4e1145f1ba974a2b7d46.js": "0c8f91cacc1d66d2bc56dfb859c4b2e9f6fe1aeb",
    "/assets/data/rin-sample-01.xml": "ec7fc751bbde79156f7d527da2acd18d2a544f5b",
    "/assets/icon.png": "a20390923c3df44fade9981fc4f017c4256e09b4",
    "/assets/icons/icon-128x128.png": "09318c3871d6314431affe2f63fd24acc2d5bcde",
    "/assets/icons/icon-144x144.png": "c883d55f40650536e8abd5e5c7b71b468c683da6",
    "/assets/icons/icon-152x152.png": "5bdad3f027c2aa52fcd2368f0694f20be2e5e01d",
    "/assets/icons/icon-192x192.png": "bc53ac542530f405933b96eb2f938f969d6ca52e",
    "/assets/icons/icon-384x384.png": "f826af86b899f32cc8af3bae1c79c17254231339",
    "/assets/icons/icon-512x512.png": "7aa9295cb6c92a49a4ee3d44ecda8adf2180024f",
    "/assets/icons/icon-72x72.png": "07670d6af9d02e9cbe0ed5e1e67e403243966300",
    "/assets/icons/icon-96x96.png": "17796a06593a00e631c0e5ca39425afcf51fb72c",
    "/assets/schemas/Audio.yaml": "35e9efc2425b1de0b6b45cd689989fed36eb7091",
    "/assets/schemas/Clip.yaml": "07f3f828d17fcb678c9f546c7d970fa776682c54",
    "/assets/schemas/Person.yaml": "80e0289dec909aba6282405c4eeb47cce8aa921f",
    "/assets/schemas/Photo.yaml": "ba27c13bb4d039d764b041b820d9917848394701",
    "/assets/schemas/Project.yaml": "dfee8d005b0a7616fbc22bb759cdaca44ed45662",
    "/assets/schemas/file.yaml": "942d1e0de0fd0439643176f9cb387e5c452bf514",
    "/assets/schemas/music-recording.yaml": "8290477fe00b711fd7983843477f39ff2c93c8f3",
    "/assets/schemas/music-release.yaml": "51bae08b5d488f06bb9aff2b078898b85915ef1c",
    "/assets/schemas/music-work.yaml": "f4112e0031802052bdbcf4df1c2898015a4aa1db",
    "/assets/schemas/payment.yaml": "2c1d1ad9fe4050848e3e96d5dd0b5a4a0838c870",
    "/assets/swagger/unsplash.json": "279da348e0f5573c80411a3dc41147fb1bd4b45d",
    "/favicon.ico": "84161b857f5c547e3699ddfbffc6d8d737542e01",
    "/index.html": "ff03b05765793dcbdad2cb03fb8783ef26cd0da5",
    "/main.c6dab967d020ecbf95fe.js": "ef239f48ffd8da1607a9c55271ababc76d308267",
    "/polyfills.eea33a3478150ded0b67.js": "137283dd3319d2aede63c96a8d52f58b43ddf56d",
    "/runtime.29054088d9cfdb04e3f5.js": "ae79bf8547fe74740e72f2bbc6fdebc93cf44448",
    "/scripts.286ee48665d1076626b8.js": "ba2eaf4085a2f102100e474bcd89861dbd5f40e5",
    "/styles.9da218e9c8e3bbce040a.css": "e0832a2e685731f1baf6feff7e2e9ac5841810c8"
  },
  "navigationUrls": [
    {
      "positive": true,
      "regex": "^\\/.*$"
    },
    {
      "positive": false,
      "regex": "^\\/(?:.+\\/)?[^/]*\\.[^/]*$"
    },
    {
      "positive": false,
      "regex": "^\\/(?:.+\\/)?[^/]*__[^/]*$"
    },
    {
      "positive": false,
      "regex": "^\\/(?:.+\\/)?[^/]*__[^/]*\\/.*$"
    }
  ]
}